{
  "code": 200,
  "message": "成功",
  "data": [
    {
      "id": 86,
      "createId": null,
      "createName": null,
      "updateId": null,
      "updateName": null,
      "createTime": "2019-06-10 10:43:35",
      "updateTime": "2020-06-23 15:43:48",
      "param": {},
      "parentId": 1,
      "name": "省",
      "dictCode": "Province",
      "hasChildren": true
    },
    {
      "id": 10000,
      "createId": null,
      "createName": null,
      "updateId": null,
      "updateName": null,
      "createTime": "2019-06-10 10:43:32",
      "updateTime": "2022-03-17 06:32:41",
      "param": {},
      "parentId": 1,
      "name": "库区类型",
      "dictCode": "AreaType",
      "hasChildren": true
    },
    {
      "id": 20000,
      "createId": null,
      "createName": null,
      "updateId": null,
      "updateName": null,
      "createTime": "2019-06-10 10:43:32",
      "updateTime": "2022-03-17 06:32:55",
      "param": {},
      "parentId": 1,
      "name": "货架类型",
      "dictCode": "HouseType",
      "hasChildren": true
    },
    {
      "id": 30000,
      "createId": null,
      "createName": null,
      "updateId": null,
      "updateName": null,
      "createTime": "2019-06-10 10:43:32",
      "updateTime": "2022-03-17 06:33:18",
      "param": {},
      "parentId": 1,
      "name": "温度类型",
      "dictCode": "TemperatureType",
      "hasChildren": true
    },
    {
      "id": 40000,
      "createId": null,
      "createName": null,
      "updateId": null,
      "updateName": null,
      "createTime": "2022-03-17 08:12:40",
      "updateTime": "2022-03-17 09:10:04",
      "param": {},
      "parentId": 1,
      "name": "检查类型",
      "dictCode": "InspectType",
      "hasChildren": true
    },
    {
      "id": 50000,
      "createId": null,
      "createName": null,
      "updateId": null,
      "updateName": null,
      "createTime": "2022-03-22 14:51:56",
      "updateTime": "2022-03-23 10:51:19",
      "param": {},
      "parentId": 1,
      "name": "盘点原因",
      "dictCode": "Reason",
      "hasChildren": true
    },
    {
      "id": 50100,
      "createId": null,
      "createName": null,
      "updateId": null,
      "updateName": null,
      "createTime": "2022-03-22 14:53:07",
      "updateTime": "2022-03-23 10:51:20",
      "param": {},
      "parentId": 1,
      "name": "维度",
      "dictCode": "Dimension",
      "hasChildren": true
    },
    {
      "id": 99100,
      "createId": null,
      "createName": null,
      "updateId": null,
      "updateName": null,
      "createTime": "2019-06-11 10:39:11",
      "updateTime": "2022-03-18 01:01:54",
      "param": {},
      "parentId": 1,
      "name": "单位",
      "dictCode": "Unit",
      "hasChildren": true
    }
  ],
  "ok": true
}


{
  "code": 200,
  "message": "成功",
  "data": {
    "records": [
      {
        "id": 37,
        "createId": 1,
        "createName": "admin",
        "updateId": 1,
        "updateName": "admin",
        "createTime": "2022-07-20 08:57:38",
        "updateTime": "2022-07-20 08:57:38",
        "param": {},
        "name": "海信 Vidda 55V1F-R 55英寸 4K超高清 超薄电视 智慧屏 1.5G+8G",
        "code": "1111",
        "barcode": "1111",
        "goodsTypeId": 100086,
        "brandName": "111",
        "saleAttr": "",
        "inspectTypeId": 40001,
        "temperatureTypeId": 30001,
        "volume": "111.00",
        "weight": "111.00",
        "unitId": 99101,
        "baseUnitId": 99102,
        "baseCount": 111,
        "status": -1,
        "skuId": 29,
        "goodsTypeName": "平板电视",
        "inspectTypeName": "免检",
        "temperatureTypeName": "常温",
        "unitName": "箱",
        "baseUnitName": "个",
        "inventoryInfoList": null
      },
      {
        "id": 27,
        "createId": null,
        "createName": null,
        "updateId": 1,
        "updateName": "admin",
        "createTime": "2022-04-22 10:08:22",
        "updateTime": "2022-04-22 10:08:22",
        "param": {},
        "name": "联想ThinkBook 14 2021款 14英寸轻薄笔记本(i5-1155G7 16G 512G 高色域",
        "code": "100027",
        "barcode": "100027",
        "goodsTypeId": 100285,
        "brandName": "联想",
        "saleAttr": "",
        "inspectTypeId": 40001,
        "temperatureTypeId": 30001,
        "volume": "1.00",
        "weight": "1.00",
        "unitId": 99101,
        "baseUnitId": 99102,
        "baseCount": 10,
        "status": -1,
        "skuId": 27,
        "goodsTypeName": "笔记本",
        "inspectTypeName": "免检",
        "temperatureTypeName": "常温",
        "unitName": "箱",
        "baseUnitName": "个",
        "inventoryInfoList": null
      },
      {
        "id": 26,
        "createId": null,
        "createName": null,
        "updateId": null,
        "updateName": null,
        "createTime": "2022-04-22 10:08:22",
        "updateTime": "2022-04-22 10:08:22",
        "param": {},
        "name": "LG gram 2021款16英寸轻薄本 16_10大画面  笔记本电脑(11代i5 16G 512G 2k屏",
        "code": "100026",
        "barcode": "100026",
        "goodsTypeId": 100285,
        "brandName": "戴尔",
        "saleAttr": "",
        "inspectTypeId": 40001,
        "temperatureTypeId": 30001,
        "volume": "1.00",
        "weight": "1.00",
        "unitId": 99101,
        "baseUnitId": 99102,
        "baseCount": 10,
        "status": 1,
        "skuId": 26,
        "goodsTypeName": "笔记本",
        "inspectTypeName": "免检",
        "temperatureTypeName": "常温",
        "unitName": "箱",
        "baseUnitName": "个",
        "inventoryInfoList": null
      },
      {
        "id": 25,
        "createId": null,
        "createName": null,
        "updateId": null,
        "updateName": null,
        "createTime": "2022-04-22 10:08:22",
        "updateTime": "2022-04-22 10:08:22",
        "param": {},
        "name": "LG gram 2021款16英寸轻薄本 16_10大画面  笔记本电脑(11代i5 16G 512G 2k屏",
        "code": "100025",
        "barcode": "100025",
        "goodsTypeId": 100285,
        "brandName": "戴尔",
        "saleAttr": "",
        "inspectTypeId": 40001,
        "temperatureTypeId": 30001,
        "volume": "1.00",
        "weight": "1.00",
        "unitId": 99101,
        "baseUnitId": 99102,
        "baseCount": 10,
        "status": 1,
        "skuId": 25,
        "goodsTypeName": "笔记本",
        "inspectTypeName": "免检",
        "temperatureTypeName": "常温",
        "unitName": "箱",
        "baseUnitName": "个",
        "inventoryInfoList": null
      },
      {
        "id": 24,
        "createId": null,
        "createName": null,
        "updateId": null,
        "updateName": null,
        "createTime": "2022-04-22 10:08:22",
        "updateTime": "2022-04-22 10:08:22",
        "param": {},
        "name": "Apple MacBook Pro 13.3 八核M1芯片 16G 512G SSD 白 笔记本电脑 轻薄本 Z11C",
        "code": "100024",
        "barcode": "100024",
        "goodsTypeId": 100285,
        "brandName": "苹果",
        "saleAttr": "",
        "inspectTypeId": 40001,
        "temperatureTypeId": 30001,
        "volume": "1.00",
        "weight": "1.00",
        "unitId": 99101,
        "baseUnitId": 99102,
        "baseCount": 10,
        "status": 1,
        "skuId": 24,
        "goodsTypeName": "笔记本",
        "inspectTypeName": "免检",
        "temperatureTypeName": "常温",
        "unitName": "箱",
        "baseUnitName": "个",
        "inventoryInfoList": null
      },
      {
        "id": 23,
        "createId": null,
        "createName": null,
        "updateId": null,
        "updateName": null,
        "createTime": "2022-04-22 10:08:22",
        "updateTime": "2022-04-22 10:08:22",
        "param": {},
        "name": "Apple MacBook Pro 13.3 八核M1芯片 16G 512G SSD 深空灰 笔记本电脑 轻薄本 Z11C",
        "code": "100023",
        "barcode": "100023",
        "goodsTypeId": 100285,
        "brandName": "苹果",
        "saleAttr": "",
        "inspectTypeId": 40001,
        "temperatureTypeId": 30001,
        "volume": "1.00",
        "weight": "1.00",
        "unitId": 99101,
        "baseUnitId": 99102,
        "baseCount": 10,
        "status": 1,
        "skuId": 23,
        "goodsTypeName": "笔记本",
        "inspectTypeName": "免检",
        "temperatureTypeName": "常温",
        "unitName": "箱",
        "baseUnitName": "个",
        "inventoryInfoList": null
      },
      {
        "id": 22,
        "createId": null,
        "createName": null,
        "updateId": 1,
        "updateName": "admin",
        "createTime": "2022-04-22 10:08:22",
        "updateTime": "2022-04-22 10:08:22",
        "param": {},
        "name": "vivo S10 5G手机 8GB+256GB 青柠 超轻薄机身  6nm旗舰芯片 拍照手机 黑",
        "code": "100022",
        "barcode": "100022",
        "goodsTypeId": 100061,
        "brandName": "VIVO",
        "saleAttr": "",
        "inspectTypeId": 40001,
        "temperatureTypeId": 30001,
        "volume": "1.00",
        "weight": "1.00",
        "unitId": 99101,
        "baseUnitId": 99102,
        "baseCount": 10,
        "status": 1,
        "skuId": 22,
        "goodsTypeName": "手机",
        "inspectTypeName": "免检",
        "temperatureTypeName": "常温",
        "unitName": "箱",
        "baseUnitName": "个",
        "inventoryInfoList": null
      },
      {
        "id": 21,
        "createId": null,
        "createName": null,
        "updateId": 1,
        "updateName": "admin",
        "createTime": "2022-04-22 10:08:22",
        "updateTime": "2022-04-22 10:08:22",
        "param": {},
        "name": "vivo S10 5G手机 8GB+256GB 青柠 超轻薄机身  6nm旗舰芯片 拍照手机 青色",
        "code": "100021",
        "barcode": "100021",
        "goodsTypeId": 100061,
        "brandName": "VIVO",
        "saleAttr": "",
        "inspectTypeId": 40001,
        "temperatureTypeId": 30001,
        "volume": "1.00",
        "weight": "1.00",
        "unitId": 99101,
        "baseUnitId": 99102,
        "baseCount": 10,
        "status": -1,
        "skuId": 21,
        "goodsTypeName": "手机",
        "inspectTypeName": "免检",
        "temperatureTypeName": "常温",
        "unitName": "箱",
        "baseUnitName": "个",
        "inventoryInfoList": null
      },
      {

        "skuId": 20,
        "goodsTypeName": "手机",
        "inspectTypeName": "免检",
        "temperatureTypeName": "常温",
        "unitName": "箱",
        "baseUnitName": "个",
        "inventoryInfoList": null
      },
      {
        "id": 19,
        "createId": null,
        "createName": null,
        "updateId": null,
        "updateName": null,
        "createTime": "2022-04-22 10:08:22",
        "updateTime": "2022-04-22 10:08:22",
        "param": {},
        "name": "vivo S10 Pro 5G手机 12GB+256GB 青柠  6nm旗舰芯片 青色",
        "code": "100019",
        "barcode": "100019",
        "goodsTypeId": 100061,
        "brandName": "VIVO",
        "saleAttr": "",
        "inspectTypeId": 40001,
        "temperatureTypeId": 30001,
        "volume": "1.00",
        "weight": "1.00",
        "unitId": 99101,
        "baseUnitId": 99102,
        "baseCount": 10,
        "status": 1,
        "skuId": 19,
        "goodsTypeName": "手机",
        "inspectTypeName": "免检",
        "temperatureTypeName": "常温",
        "unitName": "箱",
        "baseUnitName": "个",
        "inventoryInfoList": null
      }
    ],
    "total": 28,
    "size": 10,
    "current": 1,
    "orders": [],
    "optimizeCountSql": true,
    "hitCount": false,
    "countId": null,
    "maxLimit": null,
    "searchCount": true,
    "pages": 3
  },
  "ok": true
}

{
  "code": 200,
  "message": "成功",
  "data": [
    {
      "id": 40001,
      "createId": null,
      "createName": null,
      "updateId": null,
      "updateName": null,
      "createTime": "2022-03-17 16:12:55",
      "updateTime": "2022-03-17 17:10:04",
      "param": {},
      "parentId": 40000,
      "name": "免检",
      "dictCode": null,
      "hasChildren": false
    },
    {
      "id": 40002,
      "createId": null,
      "createName": null,
      "updateId": null,
      "updateName": null,
      "createTime": "2022-04-07 18:39:06",
      "updateTime": "2022-04-13 08:53:18",
      "param": {},
      "parentId": 40000,
      "name": "抽查",
      "dictCode": null,
      "hasChildren": false
    },
    {
      "id": 40003,
      "createId": null,
      "createName": null,
      "updateId": null,
      "updateName": null,
      "createTime": "2022-04-07 18:39:29",
      "updateTime": "2022-04-13 08:53:19",
      "param": {},
      "parentId": 40000,
      "name": "全检",
      "dictCode": null,
      "hasChildren": false
    }
  ],
  "ok": true
}

